process_cuwb_data/__init__.py
process_cuwb_data/__main__.py
process_cuwb_data/camera_helper.py
process_cuwb_data/camera_uwb_line_of_sight.py
process_cuwb_data/cli.py
process_cuwb_data/core.py
process_cuwb_data/filters/__init__.py
process_cuwb_data/filters/butter.py
process_cuwb_data/filters/filt_filt.py
process_cuwb_data/filters/savgol.py
process_cuwb_data/filters/sos_filt_filt.py
process_cuwb_data/find_active_tags.py
process_cuwb_data/geom_render.py
process_cuwb_data/honeycomb_imu_data.py
process_cuwb_data/honeycomb_pose_data.py
process_cuwb_data/honeycomb_service/__init__.py
process_cuwb_data/honeycomb_service/client.py
process_cuwb_data/parse_events.py
process_cuwb_data/rds_imu_data.py
process_cuwb_data/utils/__init__.py
process_cuwb_data/utils/case_insensitive_enum.py
process_cuwb_data/utils/const.py
process_cuwb_data/utils/io.py
process_cuwb_data/utils/log.py
process_cuwb_data/utils/util.py
process_cuwb_data/uwb_extract_data.py
process_cuwb_data/uwb_motion_classifier_human_activity.py
process_cuwb_data/uwb_motion_classifier_random_forest.py
process_cuwb_data/uwb_motion_classifier_tray_carry.py
process_cuwb_data/uwb_motion_distance.py
process_cuwb_data/uwb_motion_enum_carry_categories.py
process_cuwb_data/uwb_motion_enum_groundtruth_data_source.py
process_cuwb_data/uwb_motion_enum_human_activities.py
process_cuwb_data/uwb_motion_enum_interaction_types.py
process_cuwb_data/uwb_motion_events.py
process_cuwb_data/uwb_motion_features.py
process_cuwb_data/uwb_motion_filters.py
process_cuwb_data/uwb_motion_ground_truth.py
process_cuwb_data/uwb_motion_tray_interactions.py
process_cuwb_data/uwb_predict_tray_centroids.py
process_cuwb_data/visualize.py
wf_process_cuwb_data-1.16.8.dist-info/LICENSE
wf_process_cuwb_data-1.16.8.dist-info/METADATA
wf_process_cuwb_data-1.16.8.dist-info/WHEEL
wf_process_cuwb_data-1.16.8.dist-info/entry_points.txt
wf_process_cuwb_data-1.16.8.dist-info/RECORD
