Metadata-Version: 2.1
Name: wf-process-cuwb-data
Version: 1.16.8
Summary: Tools for reading, processing, and writing CUWB data
Home-page: https://github.com/WildflowerSchools/wf-process-cuwb-data
License: MIT
Author: Theodore Quinn
Author-email: ted.quinn@wildflowerschools.org
Requires-Python: >=3.8,<3.12
Classifier: Intended Audience :: Developers
Classifier: License :: OSI Approved :: MIT License
Classifier: Operating System :: OS Independent
Classifier: Programming Language :: Python
Classifier: Programming Language :: Python :: 3
Classifier: Programming Language :: Python :: 3.8
Classifier: Programming Language :: Python :: 3.9
Classifier: Programming Language :: Python :: 3.10
Classifier: Programming Language :: Python :: 3.11
Requires-Dist: boto3 (>=1.17,<2.0)
Requires-Dist: click (>=8.0.0,<9.0.0)
Requires-Dist: click-log (>=0.4.0,<0.5.0)
Requires-Dist: deprecated (>=1.2.13,<2.0.0)
Requires-Dist: matplotlib (>=3.7.0,<4.0.0)
Requires-Dist: nocasedict (>=2.0.0,<3.0.0)
Requires-Dist: numpy (>=1.20.2,<2.0.0)
Requires-Dist: pandas (>=1.2.4)
Requires-Dist: platformdirs (>=3.0.0,<4.0.0)
Requires-Dist: python-dotenv (>=1.0.0,<2.0.0)
Requires-Dist: python-slugify (>=8.0.0,<9.0.0)
Requires-Dist: pyyaml (>=6.0,<7.0)
Requires-Dist: scikit-learn (>=1.2.2,<2.0.0)
Requires-Dist: scipy (>=1.6.3,<2.0.0)
Requires-Dist: toml (>=0.10.2,<0.11.0)
Requires-Dist: torch (>=2.0.1,<3.0.0)
Requires-Dist: wf-geom-render (>=0.5.0,<0.6.0)
Requires-Dist: wf-honeycomb-io (>=2.1.1,<3.0.0)
Requires-Dist: wf-honeycomb-rds-client (>=0.3.3,<0.4.0)
Requires-Dist: wf-process-pose-data (>=6.2.0,<7.0.0)
Requires-Dist: wf-video-io (>=3.4.0,<4.0.0)
Project-URL: Repository, https://github.com/WildflowerSchools/wf-process-cuwb-data
